_distutils_hack/__init__.py
_distutils_hack/override.py
dateutil/__init__.py
dateutil/_common.py
dateutil/_version.py
dateutil/easter.py
dateutil/relativedelta.py
dateutil/rrule.py
dateutil/tzwin.py
dateutil/utils.py
dateutil/parser/__init__.py
dateutil/parser/_parser.py
dateutil/parser/isoparser.py
dateutil/tz/__init__.py
dateutil/tz/_common.py
dateutil/tz/_factories.py
dateutil/tz/tz.py
dateutil/tz/win.py
dateutil/zoneinfo/__init__.py
dateutil/zoneinfo/rebuild.py
pkg_resources/__init__.py
pkg_resources/py.typed
pkg_resources/tests/__init__.py
pkg_resources/tests/test_find_distributions.py
pkg_resources/tests/test_integration_zope_interface.py
pkg_resources/tests/test_markers.py
pkg_resources/tests/test_pkg_resources.py
pkg_resources/tests/test_resources.py
pkg_resources/tests/test_working_set.py
pyawscron/__init__.py
pyawscron/awscron.py
pyawscron/commons.py
pyawscron/occurrence.py
pyawscron/version.py
setuptools/__init__.py
setuptools/_core_metadata.py
setuptools/_entry_points.py
setuptools/_imp.py
setuptools/_importlib.py
setuptools/_itertools.py
setuptools/_normalization.py
setuptools/_path.py
setuptools/_reqs.py
setuptools/_shutil.py
setuptools/archive_util.py
setuptools/build_meta.py
setuptools/depends.py
setuptools/discovery.py
setuptools/dist.py
setuptools/errors.py
setuptools/extension.py
setuptools/glob.py
setuptools/installer.py
setuptools/launch.py
setuptools/logging.py
setuptools/modified.py
setuptools/monkey.py
setuptools/msvc.py
setuptools/namespaces.py
setuptools/package_index.py
setuptools/sandbox.py
setuptools/unicode_utils.py
setuptools/version.py
setuptools/warnings.py
setuptools/wheel.py
setuptools/windows_support.py
setuptools/_distutils/__init__.py
setuptools/_distutils/_log.py
setuptools/_distutils/_macos_compat.py
setuptools/_distutils/_modified.py
setuptools/_distutils/_msvccompiler.py
setuptools/_distutils/archive_util.py
setuptools/_distutils/ccompiler.py
setuptools/_distutils/cmd.py
setuptools/_distutils/core.py
pyawscronversion2-1.0.0.dist-info/METADATA
pyawscronversion2-1.0.0.dist-info/WHEEL
pyawscronversion2-1.0.0.dist-info/top_level.txt
pyawscronversion2-1.0.0.dist-info/RECORD
