Metadata-Version: 2.1
Name: pyawscronversion2
Version: 1.0.0
Summary: A customized version of pyawscron limited to DXC
Home-page: https://github.com/pitchblack408/pyawscron.git
Author: AWS Platform Engineering
Author-email: abc@example.com
Requires-Python: >=3.6
Requires-Dist: python-dateutil>=2.8.1
